<?xml version="1.0" encoding="UTF-8"?>
<?xml-stylesheet type="text/xsl" href="/~1mlynczak/lab05/task/inventory.xsl"?>
<inventory>
  <productGroup>
    <groupName>Nabiał</groupName>
    <products>
      <product>
        <productName>Ser</productName>
        <quantity>10</quantity>
        <price>2.50</price>
      </product>
      <product>
        <productName>Śmietana</productName>
        <quantity>15</quantity>
        <price>3.00</price>
      </product>
      <product>
        <productName>Mleko</productName>
        <quantity>10</quantity>
        <price>4.50</price>
      </product>
    </products>
  </productGroup>
  <productGroup>
    <groupName>Mięsa</groupName>
    <products>
      <product>
        <productName>Wołowina</productName>
        <quantity>2</quantity>
        <price>15.99</price>
      </product>
      <product>
        <productName>Drób</productName>
        <quantity>15</quantity>
        <price>7.58</price>
      </product>
      <product>
        <productName>Jagnięcina</productName>
        <quantity>7</quantity>
        <price>10.00</price>
      </product>
      <product>
        <productName>Wieprzowina</productName>
        <quantity>10</quantity>
        <price>12.50</price>
      </product>
    </products>
  </productGroup>
  <productGroup>
    <groupName>Owoce i Warzywa</groupName>
    <products>
      <product>
        <productName>Jabłko</productName>
        <quantity>50</quantity>
        <price>1.50</price>
      </product>
      <product>
        <productName>Gruszka</productName>
        <quantity>37</quantity>
        <price>2.35</price>
      </product>
      <product>
        <productName>Marchewka</productName>
        <quantity>13</quantity>
        <price>4.00</price>
      </product>
      <product>
        <productName>Cebula</productName>
        <quantity>10</quantity>
        <price>2.49</price>
      </product>
    </products>
  </productGroup>
</inventory>
